django_navbar/__init__.py
django_navbar/admin.py
django_navbar/apps.py
django_navbar/context_processors.py
django_navbar/locale/de/LC_MESSAGES/django.po
django_navbar/migrations/0001_initial.py
django_navbar/migrations/0001_squashed_0005_navlogo_alter_navigation_type_and_more.py
django_navbar/migrations/0002_navigation_name_navigation_order_navigation_type_and_more.py
django_navbar/migrations/0003_alter_navigation_url.py
django_navbar/migrations/0004_navigationdropdown_and_more.py
django_navbar/migrations/0005_navlogo_alter_navigation_type_and_more.py
django_navbar/migrations/0006_navigationlogo_delete_navlogo_alter_navigation_type_and_more.py
django_navbar/migrations/0007_navigation_name_de_navigation_name_en_and_more.py
django_navbar/migrations/0008_alter_navigation_options_navigationdropdown_name_de_and_more.py
django_navbar/migrations/0009_navigation_name_af_navigation_name_ar_and_more.py
django_navbar/migrations/__init__.py
django_navbar/models.py
django_navbar/translation.py
django_custom_navbar-0.0.4.dist-info/LICENSE
django_custom_navbar-0.0.4.dist-info/METADATA
django_custom_navbar-0.0.4.dist-info/WHEEL
django_custom_navbar-0.0.4.dist-info/RECORD
